temporallib/__init__.py
temporallib/auth/__init__.py
temporallib/auth/auth.py
temporallib/client/__init__.py
temporallib/client/client.py
temporallib/encryption/__init__.py
temporallib/encryption/crypt.py
temporallib/encryption/data_converter.py
temporallib/worker/__init__.py
temporallib/worker/sentry_interceptor.py
temporallib/worker/worker.py
temporal_lib_py-1.8.6.dist-info/LICENSE
temporal_lib_py-1.8.6.dist-info/METADATA
temporal_lib_py-1.8.6.dist-info/WHEEL
temporal_lib_py-1.8.6.dist-info/RECORD
