Metadata-Version: 2.1
Name: temporal-lib-py
Version: 1.8.6
Summary: A wrapper library for candid-based temporal authentication
License: LGPL-3.0
Author: gtato
Requires-Python: >=3.8,<4.0
Classifier: License :: OSI Approved :: GNU Lesser General Public License v3 (LGPLv3)
Classifier: Programming Language :: Python :: 3
Classifier: Programming Language :: Python :: 3.8
Classifier: Programming Language :: Python :: 3.9
Classifier: Programming Language :: Python :: 3.10
Classifier: Programming Language :: Python :: 3.11
Classifier: Programming Language :: Python :: 3.12
Requires-Dist: google-auth (>=2.19.1,<3.0.0)
Requires-Dist: macaroonbakery (>=1.3.1,<2.0.0)
Requires-Dist: pycryptodome (>=3.15.0,<4.0.0)
Requires-Dist: pydantic-settings (>=2.4.0,<3.0.0)
Requires-Dist: sentry-sdk (>=1.29.2,<2.0.0)
Requires-Dist: temporalio (>=1.8.0,<2.0.0)
